vortex_sdk/__init__.py
vortex_sdk/bridge.py
vortex_sdk/exceptions.py
vortex_sdk/py.typed
vortex_sdk/sdk.py
vortex_sdk/types.py
vortex_sdk_python-0.2.1.dist-info/licenses/AUTHORS.md
vortex_sdk_python-0.2.1.dist-info/licenses/LICENSE
vortex_sdk_python-0.2.1.dist-info/METADATA
vortex_sdk_python-0.2.1.dist-info/WHEEL
vortex_sdk_python-0.2.1.dist-info/top_level.txt
vortex_sdk_python-0.2.1.dist-info/RECORD
