Metadata-Version: 2.4
Name: vortex-sdk-python
Version: 0.2.1
Summary: Python wrapper for Vortex SDK using Node.js subprocess
Home-page: https://github.com/pendulum-chain/vortex
Author: Pendulum Chain
Author-email: SatoshiPay <info@satoshipay.io>
License: MIT
Project-URL: Homepage, https://github.com/pendulum-chain/vortex
Project-URL: Documentation, https://docs.vortex.pendulumchain.tech
Project-URL: Repository, https://github.com/pendulum-chain/vortex
Project-URL: Issues, https://github.com/pendulum-chain/vortex/issues
Classifier: Development Status :: 4 - Beta
Classifier: Intended Audience :: Developers
Classifier: Topic :: Software Development :: Libraries :: Python Modules
Classifier: License :: OSI Approved :: MIT License
Classifier: Programming Language :: Python :: 3
Classifier: Programming Language :: Python :: 3.9
Classifier: Programming Language :: Python :: 3.10
Classifier: Programming Language :: Python :: 3.11
Classifier: Programming Language :: Python :: 3.12
Classifier: Operating System :: OS Independent
Requires-Python: >=3.9
License-File: LICENSE
License-File: AUTHORS.md
Provides-Extra: dev
Requires-Dist: pytest>=7.0.0; extra == "dev"
Requires-Dist: pytest-cov>=4.0.0; extra == "dev"
Requires-Dist: pytest-asyncio>=0.21.0; extra == "dev"
Requires-Dist: black>=23.0.0; extra == "dev"
Requires-Dist: mypy>=1.0.0; extra == "dev"
Requires-Dist: ruff>=0.1.0; extra == "dev"
Dynamic: author
Dynamic: home-page
Dynamic: license-file
Dynamic: requires-python
